{
  "appPageId" : "bde82fd5-ea25-4e4c-ae0c-956aa2146135",
  "componentName" : "siteforce:sldsTwoCol66Layout",
  "dataProviders" : [ ],
  "id" : "510de30e-1853-4baa-98ff-e38e2fc3583e",
  "label" : "Contact Support",
  "regions" : [ {
    "id" : "3fd73889-9cf5-4043-99b9-3eea75e62c8c",
    "regionName" : "header",
    "type" : "region"
  }, {
    "components" : [ {
      "componentAttributes" : {
        "allowAttachments" : true,
        "attachmentLabel" : "Upload File",
        "buttonAlignment" : "center",
        "buttonBgColor" : "",
        "buttonBgHoverColor" : "",
        "buttonBorderColor" : "",
        "buttonMaxWidth" : "",
        "buttonRadius" : 0,
        "buttonTextColor" : "",
        "buttonTextHoverColor" : "",
        "callToAction" : false,
        "callToActionButtonText" : "",
        "callToActionText" : "",
        "callToActionUrl" : "",
        "confirmationSubtext" : "We’ll get back to you soon.",
        "confirmationText" : "Your case was created.",
        "guestQuickActionName" : "GuestCommunityCase",
        "headerSubtitle" : "Tell us how we can help.",
        "headerTitle" : "Contact Customer Support",
        "isMicrobatch" : false,
        "quickActionName" : "NewCommunityCase",
        "requestSummaryText" : "Case summary"
      },
      "componentName" : "forceCommunity:contactSupportForm",
      "id" : "bab3b8e5-e46c-4be4-8d9a-05cca439d42f",
      "renderPriority" : "NEUTRAL",
      "renditionMap" : { },
      "type" : "component"
    } ],
    "id" : "441f7cea-9146-4b8c-add9-b465e7766125",
    "regionName" : "content",
    "type" : "region"
  }, {
    "components" : [ {
      "componentAttributes" : {
        "askConfirmationQuestion" : true,
        "confirmationMessageLabel" : "Got it!",
        "deflectionSubtitle" : "Find what you need here.",
        "deflectionTitle" : "Need Answers Fast?",
        "firstQuestion" : "Did this content solve your issue?",
        "maxResults" : 6,
        "measureDeflection" : true,
        "redirectUrl" : "",
        "secondQuestion" : "Stop creating your case?",
        "showArticles" : true,
        "showDiscussions" : false,
        "topicId" : ""
      },
      "componentName" : "forceCommunity:caseDeflection",
      "id" : "54772bbe-1666-4f2c-bda0-fa99955dabc7",
      "renderPriority" : "NEUTRAL",
      "renditionMap" : { },
      "type" : "component"
    } ],
    "id" : "f245a813-a4b8-4396-af3c-39f7b15154b5",
    "regionName" : "sidebar",
    "type" : "region"
  }, {
    "id" : "80446309-13a6-4545-88e2-96f30c582d69",
    "regionName" : "footer",
    "type" : "region"
  }, {
    "components" : [ {
      "componentAttributes" : {
        "customHeadTags" : "",
        "description" : "",
        "title" : "Contact Support"
      },
      "componentName" : "forceCommunity:seoAssistant",
      "id" : "b6c0a4b2-9f7c-44d5-8933-86bdf8c85da8",
      "renditionMap" : { },
      "type" : "component"
    } ],
    "id" : "117837fd-cc43-4724-83ea-1a9de5689077",
    "regionName" : "sfdcHiddenRegion",
    "type" : "region"
  } ],
  "themeLayoutType" : "Inner",
  "type" : "view",
  "viewType" : "contactsupport"
}